[
  {
    "CdsFCBContext": "{\"FileType\":true,\"ImageExternalStorage\":true}",
    "EntitySetName": "dacrm_addresses",
    "IsHidden": false,
    "IsSampleData": false,
    "IsWritable": true,
    "LogicalName": "dacrm_address",
    "MaxGetRowsCount": 500,
    "Name": "Address",
    "NativeCDSDataSourceInfoNameMapping": {
      "createdby": "Created By",
      "createdon": "Created On",
      "createdonbehalfby": "Created By (Delegate)",
      "dacrm_address_AsyncOperations": "System Jobs",
      "dacrm_address_BulkDeleteFailures": "Bulk Delete Failures",
      "dacrm_address_MailboxTrackingFolders": "Mailbox Auto Tracking Folders",
      "dacrm_address_PrincipalObjectAttributeAccesses": "Field Sharing",
      "dacrm_address_ProcessSession": "Process Sessions",
      "dacrm_address_SyncErrors": "Sync Errors",
      "dacrm_addressid": "Address ID",
      "dacrm_addressline1floorandunit": "Address Line 1: Floor and Unit",
      "dacrm_addressline2buildingandblocknumber": "Address Line 2: Building and Block Number",
      "dacrm_addressline3streetnameandnumber": "Address Line 3: Street Name and Number",
      "dacrm_addresstypetype": "Address Type",
      "dacrm_careofco": "Care of (C/O)",
      "dacrm_chineseaddressline1floorandunit": "Chinese Address Line 1: Floor and Unit",
      "dacrm_chineseaddressline2buildingandblocknumber": "Chinese Address Line 2: Building and Block Number",
      "dacrm_chineseaddressline3streetnameandnumber": "Chinese Address Line 3: Street Name and Number",
      "dacrm_chinesecompositeaddress": "Chinese Composite Address",
      "dacrm_city": "City (To be deleted)",
      "dacrm_citylookup": "City",
      "dacrm_citystring": "City(tobedeleted)",
      "dacrm_Constituent": "Constituent Name",
      "dacrm_country": "Country (to be deleted)",
      "dacrm_countrylookup": "Country",
      "dacrm_county": "County (to be removed)",
      "dacrm_countystring": "County",
      "dacrm_description": "Description (if not constituent)",
      "dacrm_district": "District",
      "dacrm_donotmail": "Do Not Mail",
      "dacrm_donotmailreason": "Do Not Mail Reason",
      "dacrm_enddate": "End Date",
      "dacrm_englishcompositeaddress": "English Composite Address ",
      "dacrm_fax": "Fax",
      "dacrm_informationsource": "Information Source (to be deleted)",
      "dacrm_informationsourcepicklist": "Information Source",
      "dacrm_isconfidential": "Is Confidential",
      "dacrm_isinvalidaddress": "Is Invalid Address",
      "dacrm_isprimary": "Is Primary",
      "dacrm_name": "Address Name",
      "dacrm_namename": "Contact Name",
      "dacrm_postalcode": "Postal Code",
      "dacrm_postofficebox": "Post Office Box",
      "dacrm_primarycontactname": "Primary Contact Name",
      "dacrm_startdate": "Start Date",
      "dacrm_stateorprovince": "State or Province(tobedeleted)",
      "dacrm_stateorprovincelookup": "State or Province",
      "dacrm_tobeverified": "To be verified",
      "importsequencenumber": "Import Sequence Number",
      "modifiedby": "Modified By",
      "modifiedon": "Modified On",
      "modifiedonbehalfby": "Modified By (Delegate)",
      "organizationid": "Organization Id",
      "overriddencreatedon": "Record Created On",
      "statecode": "Status",
      "statuscode": "Status Reason",
      "timezoneruleversionnumber": "Time Zone Rule Version Number",
      "utcconversiontimezonecode": "UTC Conversion Time Zone Code",
      "versionnumber": "Version Number"
    },
    "PreferredName": "Address",
    "Type": "NativeCDSDataSourceInfo"
  },
  {
    "DisplayName": "Address (Views)",
    "Name": "_dacrm_address_views",
    "RelatedEntityName": "Address",
    "TrimmedViewName": true,
    "Type": "ViewInfo",
    "ViewInfoNameMapping": {
      "10aefe05-1fd0-48de-8d38-0487e6e3c058": "Address Advanced Find View",
      "1997ff5e-e91a-ee11-8f6d-000d3a08d170": "Address Import View",
      "1fbc0d67-4b24-ee11-9965-000d3a094e6b": "Chinese Address Subgrid View",
      "3bd51b81-d232-4d25-bf85-e8e0f534800b": "Address Associated View",
      "489b8064-1d28-44d7-a21e-6dbec42319e1": "Active Address",
      "4a77d18c-6124-4a5b-98b6-1c92823b5e38": "Address Lookup View",
      "4e134c5f-fd85-4cee-9c51-cc40e16c9ae7": "Inactive Address",
      "81fe0752-db23-ee11-9965-000d3a094e6b": "Chinese Address Import View"
    }
  },
  {
    "DisplayName": "Address Type (Address)",
    "Name": "dacrm_address_dacrm_addresstypetype",
    "OptionSetInfoNameMapping": {
      "128490000": "Business",
      "128490001": "Contact person",
      "128490002": "Home",
      "128490003": "Correspondence",
      "128490004": "Input by online donation form",
      "128490005": "Input by online donation processing form",
      "128490006": "Input by event registration form",
      "128490007": "Input by excel template",
      "128490008": "Input by SIS",
      "128490009": "Input by HCMS"
    },
    "OptionSetIsBooleanValued": false,
    "OptionSetIsGlobal": false,
    "OptionSetReference": {
      "OptionSetReferenceItem0": {
        "OptionSetReferenceColumnName": "dacrm_addresstypetype",
        "OptionSetReferenceEntityName": "Address"
      }
    },
    "OptionSetTypeKey": "PicklistType",
    "RelatedColumnInvariantName": "dacrm_addresstypetype",
    "RelatedEntityName": "Address",
    "Type": "OptionSetInfo"
  },
  {
    "DisplayName": "City (To be deleted) (Address)",
    "Name": "dacrm_address_dacrm_city",
    "OptionSetInfoNameMapping": {
      "128490000": "[NOT POSSIBLE TO LIST OUT ALL CITIES]"
    },
    "OptionSetIsBooleanValued": false,
    "OptionSetIsGlobal": false,
    "OptionSetReference": {
      "OptionSetReferenceItem0": {
        "OptionSetReferenceColumnName": "dacrm_city",
        "OptionSetReferenceEntityName": "Address"
      }
    },
    "OptionSetTypeKey": "PicklistType",
    "RelatedColumnInvariantName": "dacrm_city",
    "RelatedEntityName": "Address",
    "Type": "OptionSetInfo"
  },
  {
    "DisplayName": "Country (to be deleted) (Address)",
    "Name": "dacrm_address_dacrm_country",
    "OptionSetInfoNameMapping": {
      "128490000": "Afghanistan",
      "128490001": "Albania",
      "128490002": "Algeria",
      "128490003": "Andorra",
      "128490004": "Angola",
      "128490005": "Antigua and Barbuda",
      "128490006": "Argentina",
      "128490007": "Armenia",
      "128490008": "Australia",
      "128490009": "Austria",
      "128490010": "Azerbaijan",
      "128490011": "Bahamas",
      "128490012": "Bahrain",
      "128490013": "Bangladesh",
      "128490014": "Barbados",
      "128490015": "Belarus",
      "128490016": "Belgium",
      "128490017": "Belize",
      "128490018": "Benin",
      "128490019": "Bhutan",
      "128490020": "Bolivia",
      "128490021": "Bosnia and Herzegovina",
      "128490022": "Botswana",
      "128490023": "Brazil",
      "128490024": "Brunei",
      "128490025": "Bulgaria",
      "128490026": "Burkina Faso",
      "128490027": "Burundi",
      "128490028": "Cambodia",
      "128490029": "Cameroon",
      "128490030": "Canada",
      "128490031": "Cape Verde",
      "128490032": "Central African Republic",
      "128490033": "Chad",
      "128490034": "Chile",
      "128490035": "China",
      "128490036": "Colombia",
      "128490037": "Comoros",
      "128490038": "Congo (Democratic Republic of)",
      "128490039": "Congo (Republic of the)",
      "128490040": "Costa Rica",
      "128490041": "Cote d'Ivoire",
      "128490042": "Croatia",
      "128490043": "Cuba",
      "128490044": "Cyprus",
      "128490045": "Czech Republic",
      "128490046": "Denmark",
      "128490047": "Djibouti",
      "128490048": "Dominica",
      "128490049": "Dominican Republic",
      "128490050": "East Timor",
      "128490051": "Ecuador",
      "128490052": "Egypt",
      "128490053": "El Salvador",
      "128490054": "Equatorial Guinea",
      "128490055": "Eritrea",
      "128490056": "Estonia",
      "128490057": "Ethiopia",
      "128490058": "Fiji",
      "128490059": "Finland",
      "128490060": "France",
      "128490061": "Gabon",
      "128490062": "Gambia",
      "128490063": "Georgia",
      "128490064": "Germany",
      "128490065": "Ghana",
      "128490066": "Greece",
      "128490067": "Grenada",
      "128490068": "Guatemala",
      "128490069": "Guinea",
      "128490070": "Guinea-Bissau",
      "128490071": "Guyana",
      "128490072": "Haiti",
      "128490073": "Honduras",
      "128490074": "Hong Kong",
      "128490075": "Hungary",
      "128490076": "Iceland",
      "128490077": "India",
      "128490078": "Indonesia",
      "128490079": "Iran",
      "128490080": "Iraq",
      "128490081": "Ireland",
      "128490082": "Israel",
      "128490083": "Italy",
      "128490084": "Jamaica",
      "128490085": "Japan",
      "128490086": "Jordan",
      "128490087": "Kazakhstan",
      "128490088": "Kenya",
      "128490089": "Kiribati",
      "128490090": "Korea North",
      "128490091": "Korea South",
      "128490092": "Kosovo",
      "128490093": "Kuwait",
      "128490094": "Kyrgyzstan",
      "128490095": "Laos",
      "128490096": "Latvia",
      "128490097": "Lebanon",
      "128490098": "Lesotho",
      "128490099": "Liberia",
      "128490100": "Libya",
      "128490101": "Liechtenstein",
      "128490102": "Lithuania",
      "128490103": "Luxembourg",
      "128490104": "Macedonia",
      "128490105": "Madagascar",
      "128490106": "Malawi",
      "128490107": "Malaysia",
      "128490108": "Maldives",
      "128490109": "Mali",
      "128490110": "Malta",
      "128490111": "Marshall Islands",
      "128490112": "Mauritania",
      "128490113": "Mauritius",
      "128490114": "Mexico",
      "128490115": "Micronesia",
      "128490116": "Moldova",
      "128490117": "Monaco",
      "128490118": "Mongolia",
      "128490119": "Montenegro",
      "128490120": "Morocco",
      "128490121": "Mozambique",
      "128490122": "Myanmar (Burma)",
      "128490123": "Namibia",
      "128490124": "Nauru",
      "128490125": "Nepal",
      "128490126": "Netherlands",
      "128490127": "New Zealand",
      "128490128": "Nicaragua",
      "128490129": "Niger",
      "128490130": "Nigeria",
      "128490131": "Norway",
      "128490132": "Oman",
      "128490133": "Pakistan",
      "128490134": "Palau",
      "128490135": "Panama",
      "128490136": "Papua New Guinea",
      "128490137": "Paraguay",
      "128490138": "Peru",
      "128490139": "Philippines",
      "128490140": "Poland",
      "128490141": "Portugal",
      "128490142": "Qatar",
      "128490143": "Romania",
      "128490144": "Russia",
      "128490145": "Rwanda",
      "128490146": "Saint Kitts and Nevis",
      "128490147": "Saint Lucia",
      "128490148": "Saint Vincent and the Grenadines",
      "128490149": "Samoa",
      "128490150": "San Marino",
      "128490151": "Sao Tome and Principe",
      "128490152": "Saudi Arabia",
      "128490153": "Senegal",
      "128490154": "Serbia",
      "128490155": "Seychelles",
      "128490156": "Sierra Leone",
      "128490157": "Singapore",
      "128490158": "Slovakia",
      "128490159": "Slovenia",
      "128490160": "Solomon Islands",
      "128490161": "Somalia",
      "128490162": "South Africa",
      "128490163": "South Sudan",
      "128490164": "Spain",
      "128490165": "Sri Lanka",
      "128490166": "Sudan",
      "128490167": "Suriname",
      "128490168": "Swaziland",
      "128490169": "Sweden",
      "128490170": "Switzerland",
      "128490171": "Syria",
      "128490172": "Taiwan",
      "128490173": "Tajikistan",
      "128490174": "Tanzania",
      "128490175": "Thailand",
      "128490176": "Togo",
      "128490177": "Tonga",
      "128490178": "Trinidad and Tobago",
      "128490179": "Tunisia",
      "128490180": "Turkey",
      "128490181": "Turkmenistan",
      "128490182": "Tuvalu",
      "128490183": "Uganda",
      "128490184": "Ukraine",
      "128490185": "United Arab Emirates",
      "128490186": "United Kingdom",
      "128490187": "United States of America",
      "128490188": "Uruguay",
      "128490189": "Uzbekistan",
      "128490190": "Vanuatu",
      "128490191": "Vatican City (Holy See)",
      "128490192": "Venezuela",
      "128490193": "Vietnam",
      "128490194": "Yemen",
      "128490195": "Zambia",
      "128490196": "Zimbabwe"
    },
    "OptionSetIsBooleanValued": false,
    "OptionSetIsGlobal": false,
    "OptionSetReference": {
      "OptionSetReferenceItem0": {
        "OptionSetReferenceColumnName": "dacrm_country",
        "OptionSetReferenceEntityName": "Address"
      }
    },
    "OptionSetTypeKey": "PicklistType",
    "RelatedColumnInvariantName": "dacrm_country",
    "RelatedEntityName": "Address",
    "Type": "OptionSetInfo"
  },
  {
    "DisplayName": "County (to be removed) (Address)",
    "Name": "dacrm_address_dacrm_county",
    "OptionSetInfoNameMapping": {
      "128490000": "Afghanistan",
      "128490001": "Albania",
      "128490002": "Algeria",
      "128490003": "Andorra",
      "128490004": "Angola",
      "128490005": "Antigua and Barbuda",
      "128490006": "Argentina",
      "128490007": "Armenia",
      "128490008": "Australia",
      "128490009": "Austria",
      "128490010": "Azerbaijan",
      "128490011": "Bahamas",
      "128490012": "Bahrain",
      "128490013": "Bangladesh",
      "128490014": "Barbados",
      "128490015": "Belarus",
      "128490016": "Belgium",
      "128490017": "Belize",
      "128490018": "Benin",
      "128490019": "Bhutan",
      "128490020": "Bolivia",
      "128490021": "Bosnia and Herzegovina",
      "128490022": "Botswana",
      "128490023": "Brazil",
      "128490024": "Brunei",
      "128490025": "Bulgaria",
      "128490026": "Burkina Faso",
      "128490027": "Burundi",
      "128490028": "Cambodia",
      "128490029": "Cameroon",
      "128490030": "Canada",
      "128490031": "Cape Verde",
      "128490032": "Central African Republic",
      "128490033": "Chad",
      "128490034": "Chile",
      "128490035": "China",
      "128490036": "Colombia",
      "128490037": "Comoros",
      "128490038": "Congo (Democratic Republic of)",
      "128490039": "Congo (Republic of the)",
      "128490040": "Costa Rica",
      "128490041": "Cote d'Ivoire",
      "128490042": "Croatia",
      "128490043": "Cuba",
      "128490044": "Cyprus",
      "128490045": "Czech Republic",
      "128490046": "Denmark",
      "128490047": "Djibouti",
      "128490048": "Dominica",
      "128490049": "Dominican Republic",
      "128490050": "East Timor",
      "128490051": "Ecuador",
      "128490052": "Egypt",
      "128490053": "El Salvador",
      "128490054": "Equatorial Guinea",
      "128490055": "Eritrea",
      "128490056": "Estonia",
      "128490057": "Ethiopia",
      "128490058": "Fiji",
      "128490059": "Finland",
      "128490060": "France",
      "128490061": "Gabon",
      "128490062": "Gambia",
      "128490063": "Georgia",
      "128490064": "Germany",
      "128490065": "Ghana",
      "128490066": "Greece",
      "128490067": "Grenada",
      "128490068": "Guatemala",
      "128490069": "Guinea",
      "128490070": "Guinea-Bissau",
      "128490071": "Guyana",
      "128490072": "Haiti",
      "128490073": "Honduras",
      "128490074": "Hong Kong",
      "128490075": "Hungary",
      "128490076": "Iceland",
      "128490077": "India",
      "128490078": "Indonesia",
      "128490079": "Iran",
      "128490080": "Iraq",
      "128490081": "Ireland",
      "128490082": "Israel",
      "128490083": "Italy",
      "128490084": "Jamaica",
      "128490085": "Japan",
      "128490086": "Jordan",
      "128490087": "Kazakhstan",
      "128490088": "Kenya",
      "128490089": "Kiribati",
      "128490090": "Korea North",
      "128490091": "Korea South",
      "128490092": "Kosovo",
      "128490093": "Kuwait",
      "128490094": "Kyrgyzstan",
      "128490095": "Laos",
      "128490096": "Latvia",
      "128490097": "Lebanon",
      "128490098": "Lesotho",
      "128490099": "Liberia",
      "128490100": "Libya",
      "128490101": "Liechtenstein",
      "128490102": "Lithuania",
      "128490103": "Luxembourg",
      "128490104": "Macedonia",
      "128490105": "Madagascar",
      "128490106": "Malawi",
      "128490107": "Malaysia",
      "128490108": "Maldives",
      "128490109": "Mali",
      "128490110": "Malta",
      "128490111": "Marshall Islands",
      "128490112": "Mauritania",
      "128490113": "Mauritius",
      "128490114": "Mexico",
      "128490115": "Micronesia",
      "128490116": "Moldova",
      "128490117": "Monaco",
      "128490118": "Mongolia",
      "128490119": "Montenegro",
      "128490120": "Morocco",
      "128490121": "Mozambique",
      "128490122": "Myanmar (Burma)",
      "128490123": "Namibia",
      "128490124": "Nauru",
      "128490125": "Nepal",
      "128490126": "Netherlands",
      "128490127": "New Zealand",
      "128490128": "Nicaragua",
      "128490129": "Niger",
      "128490130": "Nigeria",
      "128490131": "Norway",
      "128490132": "Oman",
      "128490133": "Pakistan",
      "128490134": "Palau",
      "128490135": "Panama",
      "128490136": "Papua New Guinea",
      "128490137": "Paraguay",
      "128490138": "Peru",
      "128490139": "Philippines",
      "128490140": "Poland",
      "128490141": "Portugal",
      "128490142": "Qatar",
      "128490143": "Romania",
      "128490144": "Russia",
      "128490145": "Rwanda",
      "128490146": "Saint Kitts and Nevis",
      "128490147": "Saint Lucia",
      "128490148": "Saint Vincent and the Grenadines",
      "128490149": "Samoa",
      "128490150": "San Marino",
      "128490151": "Sao Tome and Principe",
      "128490152": "Saudi Arabia",
      "128490153": "Senegal",
      "128490154": "Serbia",
      "128490155": "Seychelles",
      "128490156": "Sierra Leone",
      "128490157": "Singapore",
      "128490158": "Slovakia",
      "128490159": "Slovenia",
      "128490160": "Solomon Islands",
      "128490161": "Somalia",
      "128490162": "South Africa",
      "128490163": "South Sudan",
      "128490164": "Spain",
      "128490165": "Sri Lanka",
      "128490166": "Sudan",
      "128490167": "Suriname",
      "128490168": "Swaziland",
      "128490169": "Sweden",
      "128490170": "Switzerland",
      "128490171": "Syria",
      "128490172": "Taiwan",
      "128490173": "Tajikistan",
      "128490174": "Tanzania",
      "128490175": "Thailand",
      "128490176": "Togo",
      "128490177": "Tonga",
      "128490178": "Trinidad and Tobago",
      "128490179": "Tunisia",
      "128490180": "Turkey",
      "128490181": "Turkmenistan",
      "128490182": "Tuvalu",
      "128490183": "Uganda",
      "128490184": "Ukraine",
      "128490185": "United Arab Emirates",
      "128490186": "United Kingdom",
      "128490187": "United States of America",
      "128490188": "Uruguay",
      "128490189": "Uzbekistan",
      "128490190": "Vanuatu",
      "128490191": "Vatican City (Holy See)",
      "128490192": "Venezuela",
      "128490193": "Vietnam",
      "128490194": "Yemen",
      "128490195": "Zambia",
      "128490196": "Zimbabwe"
    },
    "OptionSetIsBooleanValued": false,
    "OptionSetIsGlobal": false,
    "OptionSetReference": {
      "OptionSetReferenceItem0": {
        "OptionSetReferenceColumnName": "dacrm_county",
        "OptionSetReferenceEntityName": "Address"
      }
    },
    "OptionSetTypeKey": "PicklistType",
    "RelatedColumnInvariantName": "dacrm_county",
    "RelatedEntityName": "Address",
    "Type": "OptionSetInfo"
  },
  {
    "DisplayName": "Do Not Mail (Address)",
    "Name": "dacrm_address_dacrm_donotmail",
    "OptionSetInfoNameMapping": {
      "0": "No",
      "1": "Yes"
    },
    "OptionSetIsBooleanValued": true,
    "OptionSetIsGlobal": false,
    "OptionSetReference": {
      "OptionSetReferenceItem0": {
        "OptionSetReferenceColumnName": "dacrm_donotmail",
        "OptionSetReferenceEntityName": "Address"
      }
    },
    "OptionSetTypeKey": "BooleanType",
    "RelatedColumnInvariantName": "dacrm_donotmail",
    "RelatedEntityName": "Address",
    "Type": "OptionSetInfo"
  },
  {
    "DisplayName": "Do Not Mail Reason (Address)",
    "Name": "dacrm_address_dacrm_donotmailreason",
    "OptionSetInfoNameMapping": {
      "128490000": "Uninterested",
      "128490001": "Moved",
      "128490002": "Deceased",
      "128490003": "Wrong recipient",
      "128490004": "Privacy",
      "128490005": "Security"
    },
    "OptionSetIsBooleanValued": false,
    "OptionSetIsGlobal": false,
    "OptionSetReference": {
      "OptionSetReferenceItem0": {
        "OptionSetReferenceColumnName": "dacrm_donotmailreason",
        "OptionSetReferenceEntityName": "Address"
      }
    },
    "OptionSetTypeKey": "PicklistType",
    "RelatedColumnInvariantName": "dacrm_donotmailreason",
    "RelatedEntityName": "Address",
    "Type": "OptionSetInfo"
  },
  {
    "DisplayName": "Information Source (Address)",
    "Name": "dacrm_address_dacrm_informationsourcepicklist",
    "OptionSetInfoNameMapping": {
      "128490000": "SIS",
      "128490001": "HCM",
      "128490002": "Online Contact Update Form",
      "128490003": "FANS",
      "128490004": "Blackbaud",
      "128490005": "Event Registration Form",
      "128490006": "Online Giving Form",
      "128490007": "Online Donation Processing Form",
      "128490008": "CRM"
    },
    "OptionSetIsBooleanValued": false,
    "OptionSetIsGlobal": false,
    "OptionSetReference": {
      "OptionSetReferenceItem0": {
        "OptionSetReferenceColumnName": "dacrm_informationsourcepicklist",
        "OptionSetReferenceEntityName": "Address"
      }
    },
    "OptionSetTypeKey": "PicklistType",
    "RelatedColumnInvariantName": "dacrm_informationsourcepicklist",
    "RelatedEntityName": "Address",
    "Type": "OptionSetInfo"
  },
  {
    "DisplayName": "Is Confidential (Address)",
    "Name": "dacrm_address_dacrm_isconfidential",
    "OptionSetInfoNameMapping": {
      "0": "No",
      "1": "Yes"
    },
    "OptionSetIsBooleanValued": true,
    "OptionSetIsGlobal": false,
    "OptionSetReference": {
      "OptionSetReferenceItem0": {
        "OptionSetReferenceColumnName": "dacrm_isconfidential",
        "OptionSetReferenceEntityName": "Address"
      }
    },
    "OptionSetTypeKey": "BooleanType",
    "RelatedColumnInvariantName": "dacrm_isconfidential",
    "RelatedEntityName": "Address",
    "Type": "OptionSetInfo"
  },
  {
    "DisplayName": "Is Invalid Address (Address)",
    "Name": "dacrm_address_dacrm_isinvalidaddress",
    "OptionSetInfoNameMapping": {
      "0": "No",
      "1": "Yes"
    },
    "OptionSetIsBooleanValued": true,
    "OptionSetIsGlobal": false,
    "OptionSetReference": {
      "OptionSetReferenceItem0": {
        "OptionSetReferenceColumnName": "dacrm_isinvalidaddress",
        "OptionSetReferenceEntityName": "Address"
      }
    },
    "OptionSetTypeKey": "BooleanType",
    "RelatedColumnInvariantName": "dacrm_isinvalidaddress",
    "RelatedEntityName": "Address",
    "Type": "OptionSetInfo"
  },
  {
    "DisplayName": "Is Primary (Address)",
    "Name": "dacrm_address_dacrm_isprimary",
    "OptionSetInfoNameMapping": {
      "0": "No",
      "1": "Yes"
    },
    "OptionSetIsBooleanValued": true,
    "OptionSetIsGlobal": false,
    "OptionSetReference": {
      "OptionSetReferenceItem0": {
        "OptionSetReferenceColumnName": "dacrm_isprimary",
        "OptionSetReferenceEntityName": "Address"
      }
    },
    "OptionSetTypeKey": "BooleanType",
    "RelatedColumnInvariantName": "dacrm_isprimary",
    "RelatedEntityName": "Address",
    "Type": "OptionSetInfo"
  },
  {
    "DisplayName": "State or Province(tobedeleted) (Address)",
    "Name": "dacrm_address_dacrm_stateorprovince",
    "OptionSetInfoNameMapping": {
      "128490000": "Alabama",
      "128490001": "Alaska",
      "128490002": "Arizona",
      "128490003": "Arkansas",
      "128490004": "California",
      "128490005": "Colorado",
      "128490006": "Connecticut",
      "128490007": "Delaware",
      "128490008": "Florida",
      "128490009": "Georgia",
      "128490010": "Hawaii",
      "128490011": "Idaho",
      "128490012": "Illinois",
      "128490013": "Indiana",
      "128490014": "Iowa",
      "128490015": "Kansas",
      "128490016": "Kentucky",
      "128490017": "Louisiana",
      "128490018": "Maine",
      "128490019": "Maryland",
      "128490020": "Massachusetts",
      "128490021": "Michigan",
      "128490022": "Minnesota",
      "128490023": "Mississippi",
      "128490024": "Missouri",
      "128490025": "Montana",
      "128490026": "Nebraska",
      "128490027": "Nevada",
      "128490028": "New Hampshire",
      "128490029": "New Jersey",
      "128490030": "New Mexico",
      "128490031": "New York",
      "128490032": "North Carolina",
      "128490033": "North Dakota",
      "128490034": "Ohio",
      "128490035": "Oklahoma",
      "128490036": "Oregon",
      "128490037": "Pennsylvania",
      "128490038": "Rhode Island",
      "128490039": "South Carolina",
      "128490040": "South Dakota",
      "128490041": "Tennessee",
      "128490042": "Texas",
      "128490043": "Utah",
      "128490044": "Vermont",
      "128490045": "Virginia",
      "128490046": "Washington",
      "128490047": "West Virginia",
      "128490048": "Wisconsin",
      "128490049": "Wyoming",
      "128490050": "Alberta",
      "128490051": "British Columbia",
      "128490052": "Manitoba",
      "128490053": "New Brunswick",
      "128490054": "Newfoundland and Labrador",
      "128490055": "Northwest Territories",
      "128490056": "Nova Scotia",
      "128490057": "Nunavut",
      "128490058": "Ontario",
      "128490059": "Prince Edward\u00A0Island",
      "128490060": "Quebec",
      "128490061": "Saskatchewan",
      "128490062": "Yukon"
    },
    "OptionSetIsBooleanValued": false,
    "OptionSetIsGlobal": false,
    "OptionSetReference": {
      "OptionSetReferenceItem0": {
        "OptionSetReferenceColumnName": "dacrm_stateorprovince",
        "OptionSetReferenceEntityName": "Address"
      }
    },
    "OptionSetTypeKey": "PicklistType",
    "RelatedColumnInvariantName": "dacrm_stateorprovince",
    "RelatedEntityName": "Address",
    "Type": "OptionSetInfo"
  },
  {
    "DisplayName": "To be verified (Address)",
    "Name": "dacrm_address_dacrm_tobeverified",
    "OptionSetInfoNameMapping": {
      "0": "False",
      "1": "True"
    },
    "OptionSetIsBooleanValued": true,
    "OptionSetIsGlobal": false,
    "OptionSetReference": {
      "OptionSetReferenceItem0": {
        "OptionSetReferenceColumnName": "dacrm_tobeverified",
        "OptionSetReferenceEntityName": "Address"
      }
    },
    "OptionSetTypeKey": "BooleanType",
    "RelatedColumnInvariantName": "dacrm_tobeverified",
    "RelatedEntityName": "Address",
    "Type": "OptionSetInfo"
  },
  {
    "DisplayName": "Status (Address)",
    "Name": "dacrm_address_statecode",
    "OptionSetInfoNameMapping": {
      "0": "Active",
      "1": "Inactive"
    },
    "OptionSetIsBooleanValued": false,
    "OptionSetIsGlobal": false,
    "OptionSetReference": {
      "OptionSetReferenceItem0": {
        "OptionSetReferenceColumnName": "statecode",
        "OptionSetReferenceEntityName": "Address"
      }
    },
    "OptionSetTypeKey": "StateType",
    "RelatedColumnInvariantName": "statecode",
    "RelatedEntityName": "Address",
    "Type": "OptionSetInfo"
  },
  {
    "DisplayName": "Status Reason (Address)",
    "Name": "dacrm_address_statuscode",
    "OptionSetInfoNameMapping": {
      "1": "Active",
      "2": "Inactive"
    },
    "OptionSetIsBooleanValued": false,
    "OptionSetIsGlobal": false,
    "OptionSetReference": {
      "OptionSetReferenceItem0": {
        "OptionSetReferenceColumnName": "statuscode",
        "OptionSetReferenceEntityName": "Address"
      }
    },
    "OptionSetTypeKey": "StatusType",
    "RelatedColumnInvariantName": "statuscode",
    "RelatedEntityName": "Address",
    "Type": "OptionSetInfo"
  },
  {
    "DisplayName": "Hong Kong District",
    "Name": "dacrm_hongkongdistrict",
    "OptionSetInfoNameMapping": {
      "128490000": "HK Island",
      "128490001": "Kowloon",
      "128490002": "New Territories"
    },
    "OptionSetIsBooleanValued": false,
    "OptionSetIsGlobal": true,
    "OptionSetReference": {
      "OptionSetReferenceItem0": {
        "OptionSetReferenceColumnName": "dacrm_district",
        "OptionSetReferenceEntityName": "Address"
      }
    },
    "OptionSetTypeKey": "PicklistType",
    "RelatedColumnInvariantName": "dacrm_district",
    "RelatedEntityName": "Address",
    "Type": "OptionSetInfo"
  }
]